macrolibs/__init__.py
macrolibs/filemacros/__init__.py
macrolibs/filemacros/filemacros.py
macrolibs/filemacros/jsonmacros.py
macrolibs/typemacros/__init__.py
macrolibs/typemacros/typemacros.py
macrolibs-0.0.41.dist-info/METADATA
macrolibs-0.0.41.dist-info/WHEEL
macrolibs-0.0.41.dist-info/top_level.txt
macrolibs-0.0.41.dist-info/RECORD
