Metadata-Version: 2.1
Name: macrolibs
Version: 0.0.41
Summary: All of my macros in one place!
Home-page: https://github.com/Casey-Litmer/Utilities
Author: Casey Litmer
Author-email: litmerc@msn.com
License: MIT
Classifier: License :: OSI Approved :: MIT License
Classifier: Programming Language :: Python :: 3
Classifier: Operating System :: OS Independent
Requires-Python: >=3.6
